MANIFEST.in
requirements.txt
setup.py
test_requirements.txt
version.txt
cloudshell/__init__.py
cloudshell/traffic/__init__.py
cloudshell/traffic/teravm/__init__.py
cloudshell/traffic/teravm/controller/__init__.py
cloudshell/traffic/teravm/controller/configuration_attributes_structure.py
cloudshell/traffic/teravm/controller/constants.py
cloudshell/traffic/teravm/controller/quali_rest_api_helper.py
cloudshell/traffic/teravm/controller/flows/__init__.py
cloudshell/traffic/teravm/controller/flows/cleanup_flow.py
cloudshell/traffic/teravm/controller/flows/download_configuration_file_flow.py
cloudshell/traffic/teravm/controller/flows/load_configuration_file_flow.py
cloudshell/traffic/teravm/controller/flows/results_flow.py
cloudshell/traffic/teravm/controller/flows/start_tests_flow.py
cloudshell/traffic/teravm/controller/flows/stop_tests_flow.py
cloudshell/traffic/teravm/controller/runners/__init__.py
cloudshell/traffic/teravm/controller/runners/cleanup_runner.py
cloudshell/traffic/teravm/controller/runners/load_config_runner.py
cloudshell/traffic/teravm/controller/runners/results_runner.py
cloudshell/traffic/teravm/controller/runners/tvm_tests_runner.py
cloudshell_tg_teravm_controller.egg-info/PKG-INFO
cloudshell_tg_teravm_controller.egg-info/SOURCES.txt
cloudshell_tg_teravm_controller.egg-info/dependency_links.txt
cloudshell_tg_teravm_controller.egg-info/requires.txt
cloudshell_tg_teravm_controller.egg-info/top_level.txt