Metadata-Version: 1.0
Name: cloudshell-tg-teravm-controller
Version: 1.2.0
Summary: QualiSystems Python package
Home-page: https://github.com/QualiSystems/cloudshell-tg-teravm-controller
Author: QualiSystems
Author-email: info@qualisystems.com
License: UNKNOWN
Platform: UNKNOWN
